{
	"info": {
		"_postman_id": "229da1b3-5325-4265-b78f-41345b6281d4",
		"name": "Productos-nest",
		"schema": "https://schema.getpostman.com/json/collection/v2.1.0/collection.json",
		"_exporter_id": "37605902"
	},
	"item": [
		{
			"name": "all-productos",
			"request": {
				"method": "GET",
				"header": [],
				"url": {
					"raw": "http://localhost:4000/productos",
					"protocol": "http",
					"host": [
						"localhost"
					],
					"port": "4000",
					"path": [
						"productos"
					]
				}
			},
			"response": []
		},
		{
			"name": "producto-id",
			"request": {
				"method": "GET",
				"header": [],
				"url": {
					"raw": "http://localhost:4000/productos/4",
					"protocol": "http",
					"host": [
						"localhost"
					],
					"port": "4000",
					"path": [
						"productos",
						"4"
					]
				}
			},
			"response": []
		},
		{
			"name": "add",
			"request": {
				"method": "POST",
				"header": [],
				"body": {
					"mode": "raw",
					"raw": "{\r\n    \"nombre\" : \"Samsung Smart TV\",\r\n    \"descripcion\" : \"Televisores samsung\",\r\n    \"precio\": 2499.99,\r\n    \"stock\": 150\r\n}",
					"options": {
						"raw": {
							"language": "json"
						}
					}
				},
				"url": {
					"raw": "http://localhost:4000/productos",
					"protocol": "http",
					"host": [
						"localhost"
					],
					"port": "4000",
					"path": [
						"productos"
					]
				}
			},
			"response": []
		},
		{
			"name": "edit",
			"request": {
				"method": "PUT",
				"header": [],
				"body": {
					"mode": "raw",
					"raw": "{\r\n    \"nombre\" : \"Samsung Smart TV\",\r\n    \"descripcion\" : \"AEA\",\r\n    \"precio\": 2499.99,\r\n    \"stock\": 150\r\n}",
					"options": {
						"raw": {
							"language": "json"
						}
					}
				},
				"url": {
					"raw": "http://localhost:4000/4",
					"protocol": "http",
					"host": [
						"localhost"
					],
					"port": "4000",
					"path": [
						"4"
					]
				}
			},
			"response": []
		},
		{
			"name": "delete",
			"request": {
				"method": "DELETE",
				"header": [],
				"body": {
					"mode": "raw",
					"raw": "",
					"options": {
						"raw": {
							"language": "json"
						}
					}
				},
				"url": {
					"raw": "http://localhost:4000/productos/4",
					"protocol": "http",
					"host": [
						"localhost"
					],
					"port": "4000",
					"path": [
						"productos",
						"4"
					]
				}
			},
			"response": []
		}
	]
}